tkinteruserinput/LICENSE
tkinteruserinput/README.MD
tkinteruserinput/__init__.py
tkinteruserinput/requirements.txt
tkinteruserinput/thirdparty.json
tkinteruserinput-0.11.dist-info/LICENSE.rst
tkinteruserinput-0.11.dist-info/METADATA
tkinteruserinput-0.11.dist-info/WHEEL
tkinteruserinput-0.11.dist-info/top_level.txt
tkinteruserinput-0.11.dist-info/RECORD
