Metadata-Version: 2.1
Name: tkinteruserinput
Version: 0.11
Summary: Pop-ups to get input from the user - tkinter
Home-page: https://github.com/hansalemaos/tkinteruserinput
Author: Johannes Fischer
Author-email: aulasparticularesdealemaosp@gmail.com
License: MIT
Keywords: tkinter
Classifier: Development Status :: 4 - Beta
Classifier: Programming Language :: Python :: 3 :: Only
Classifier: Programming Language :: Python :: 3.10
Classifier: Topic :: Software Development :: Libraries :: Python Modules
Classifier: Topic :: Utilities
License-File: LICENSE.rst
